bubblepy.py
bubblepy-1.0.dist-info/DESCRIPTION.rst
bubblepy-1.0.dist-info/METADATA
bubblepy-1.0.dist-info/RECORD
bubblepy-1.0.dist-info/WHEEL
bubblepy-1.0.dist-info/metadata.json
bubblepy-1.0.dist-info/top_level.txt
