Metadata-Version: 2.0
Name: bubblepy
Version: 1.0
Summary: Bubble Babble Binary Data Encoding
Home-page: https://github.com/zefciu/bubblepy
Author: Szymon Pyżalski
Author-email: zefciu <szymon@pythonista.net>
License: UNKNOWN
Platform: UNKNOWN
Classifier: Development Status :: 5 - Production/Stable
Classifier: Intended Audience :: Developers
Classifier: License :: OSI Approved :: GNU Lesser General Public License v3 or later (LGPLv3+)
Classifier: Programming Language :: Python :: 2.7
Classifier: Programming Language :: Python :: 3.4
Classifier: Programming Language :: Python :: 3.5
Requires-Dist: six (>=1.10.0)
